Metadata-Version: 2.1
Name: Microservice_ml_classifier
Version: 0.0.0
Summary: Simple classifier to be used in production
Home-page: https://github.com/VLavado/Microservice_ml_classifier
Author: Victor Lavado
License: MIT License
Requires-Python: >=3.8
License-File: LICENSE
